fund_stack_cli/__init__.py
fund_stack_cli/auth_service.py
fund_stack_cli/budget_service.py
fund_stack_cli/cli.py
fund_stack_cli/firebase_config.py
fund_stack_cli/main.py
fund_stack_cli/report_service.py
fund_stack_cli/wallet_service.py
fund_stack_cli-0.1.0.dist-info/licenses/LICENSE
fund_stack_cli-0.1.0.dist-info/METADATA
fund_stack_cli-0.1.0.dist-info/WHEEL
fund_stack_cli-0.1.0.dist-info/entry_points.txt
fund_stack_cli-0.1.0.dist-info/top_level.txt
fund_stack_cli-0.1.0.dist-info/RECORD
