Metadata-Version: 2.4
Name: fund-stack-cli
Version: 0.1.0
Summary: A comprehensive personal finance management CLI tool.
Home-page: https://github.com/ItzSouraseez/fund-stack-cli
Author: Sourashis Ghosh Roy
Author-email: sourashis@example.com
Classifier: Programming Language :: Python :: 3
Classifier: License :: OSI Approved :: MIT License
Classifier: Operating System :: OS Independent
Requires-Python: >=3.6
License-File: LICENSE
Requires-Dist: requests
Requires-Dist: rich
Requires-Dist: google-genai
Dynamic: author
Dynamic: author-email
Dynamic: classifier
Dynamic: description
Dynamic: description-content-type
Dynamic: home-page
Dynamic: license-file
Dynamic: requires-dist
Dynamic: requires-python
Dynamic: summary
